pytorch_dice_loss/__init__.py
pytorch_dice_loss/loss.py
pytorch_dice_loss-0.1.1.dist-info/LICENSE
pytorch_dice_loss-0.1.1.dist-info/WHEEL
pytorch_dice_loss-0.1.1.dist-info/METADATA
pytorch_dice_loss-0.1.1.dist-info/RECORD
